airflow/providers/common/sql/LICENSE
airflow/providers/common/sql/README_API.md
airflow/providers/common/sql/__init__.py
airflow/providers/common/sql/get_provider_info.py
airflow/providers/common/sql/get_provider_info.pyi
airflow/providers/common/sql/dialects/__init__.py
airflow/providers/common/sql/dialects/dialect.py
airflow/providers/common/sql/dialects/dialect.pyi
airflow/providers/common/sql/doc/adr/0001-record-architecture-decisions.md
airflow/providers/common/sql/doc/adr/0002-return-common-data-structure-from-dbapihook-derived-hooks.md
airflow/providers/common/sql/doc/adr/0003-introduce-notion-of-dialects-in-dbapihook.md
airflow/providers/common/sql/hooks/__init__.py
airflow/providers/common/sql/hooks/handlers.py
airflow/providers/common/sql/hooks/handlers.pyi
airflow/providers/common/sql/hooks/sql.py
airflow/providers/common/sql/hooks/sql.pyi
airflow/providers/common/sql/operators/__init__.py
airflow/providers/common/sql/operators/sql.py
airflow/providers/common/sql/sensors/__init__.py
airflow/providers/common/sql/sensors/sql.py
airflow/providers/common/sql/sensors/sql.pyi
apache_airflow_providers_common_sql-1.22.0.dist-info/entry_points.txt
apache_airflow_providers_common_sql-1.22.0.dist-info/WHEEL
apache_airflow_providers_common_sql-1.22.0.dist-info/METADATA
apache_airflow_providers_common_sql-1.22.0.dist-info/RECORD
